{
  "gitSyncId": "66f13446f75d0d57e7f48b12_70c36f78-3a81-494c-81e7-637b675e7682",
  "id": "Comprar_getCard.getCard",
  "pluginId": "js-plugin",
  "pluginType": "JS",
  "unpublishedAction": {
    "actionConfiguration": {
      "encodeParamsToggle": true,
      "jsArguments": [],
      "paginationType": "NONE",
      "timeoutInMillisecond": 10000
    },
    "collectionId": "Comprar_getCard",
    "confirmBeforeExecute": false,
    "datasource": {
      "isAutoGenerated": false,
      "name": "UNUSED_DATASOURCE",
      "pluginId": "js-plugin"
    },
    "dynamicBindingPathList": [
      {
        "key": "body"
      }
    ],
    "executeOnLoad": false,
    "fullyQualifiedName": "getCard.getCard",
    "name": "getCard",
    "pageId": "Comprar",
    "userSetOnLoad": false
  }
}