{
  "gitSyncId": "66f13446f75d0d57e7f48b12_21a6e436-e019-4c50-9238-329da7999b42",
  "unpublishedPage": {
    "isHidden": false,
    "layouts": [
      {
        "dsl": {
          "backgroundColor": "none",
          "bottomRow": 570,
          "canExtend": true,
          "containerStyle": "none",
          "detachFromLayout": true,
          "dynamicBindingPathList": [],
          "dynamicTriggerPathList": [],
          "leftColumn": 0,
          "minHeight": 1292,
          "parentColumnSpace": 1,
          "parentRowSpace": 1,
          "rightColumn": 4896,
          "snapColumns": 64,
          "snapRows": 124,
          "topRow": 0,
          "type": "CANVAS_WIDGET",
          "version": 90,
          "widgetId": "0",
          "widgetName": "MainContainer"
        }
      }
    ],
    "name": "Dashboard",
    "slug": "dashboard"
  }
}